nxopen/__init__.py
nxopen/cad/__init__.py
nxopen/cad/code.py
nxopen/cae/__init__.py
nxopen/cae/postprocessing.py
nxopen/cae/preprocessing.py
nxopen/tools/__init__.py
nxopen/tools/excel.py
nxopen-0.0.1.dist-info/METADATA
nxopen-0.0.1.dist-info/WHEEL
nxopen-0.0.1.dist-info/licenses/LICENSE
nxopen-0.0.1.dist-info/RECORD
